LICENSE
README.md
setup.cfg
setup.py
invertransforms/__init__.py
invertransforms/affine.py
invertransforms/color.py
invertransforms/crop_pad.py
invertransforms/lib.py
invertransforms/perpective.py
invertransforms/resize.py
invertransforms/sequence.py
invertransforms/tensors.py
invertransforms/util_functions.py
invertransforms.egg-info/PKG-INFO
invertransforms.egg-info/SOURCES.txt
invertransforms.egg-info/dependency_links.txt
invertransforms.egg-info/requires.txt
invertransforms.egg-info/top_level.txt
tests/__init__.py
tests/invertible_test_case.py
tests/test_affine.py
tests/test_center_crop.py
tests/test_color_jitter.py
tests/test_compose.py
tests/test_crop.py
tests/test_five_crop.py
tests/test_grayscale.py
tests/test_identity.py
tests/test_invertible.py
tests/test_lambda.py
tests/test_linear_transformation.py
tests/test_normalize.py
tests/test_pad.py
tests/test_perspective.py
tests/test_random_erasing.py
tests/test_random_flip.py
tests/test_random_resized_crop.py
tests/test_random_transforms.py
tests/test_resize.py
tests/test_rotation.py
tests/test_ten_crop.py
tests/test_transform_if.py