Metadata-Version: 2.1
Name: invertransforms
Version: 0.2.0
Summary: A library which turns torchvision transformations invertible and replayable.
Home-page: https://github.com/gregunz/{name}
Author: gregunz
Author-email: mail@gregunx.io
License: BSD 3-Clause
Keywords: invertible,transforms,transformations,torchvision,data,augmentation,replay,replayable,invertransforms
Platform: any
Classifier: Development Status :: 3 - Alpha
Classifier: Programming Language :: Python :: 3.6
